users/__init__.py
users/admin.py
users/apps.py
users/forms.py
users/managers.py
users/models.py
users/tests.py
users/views.py
users/migrations/0001_initial.py
users/migrations/0002_user_identify_code.py
users/migrations/__init__.py
django_yessenov_users-0.0.1.dist-info/LICENSE
django_yessenov_users-0.0.1.dist-info/METADATA
django_yessenov_users-0.0.1.dist-info/WHEEL
django_yessenov_users-0.0.1.dist-info/top_level.txt
django_yessenov_users-0.0.1.dist-info/RECORD
