Metadata-Version: 2.1
Name: django-yessenov-users
Version: 0.0.1
Summary: Данная библиотека содержит модель пользователя для всех проектов
Home-page: https://github.com/yessenovuniversity/django-users
Author: Nauryzbek Aitbayev
Author-email: nauryzbek.aitbayev@yu.edu.kz
License: UNKNOWN
Platform: UNKNOWN
Classifier: Environment :: Web Environment
Classifier: Framework :: Django
Classifier: Programming Language :: Python :: 3
Classifier: License :: Other/Proprietary License
Classifier: Operating System :: OS Independent
Requires-Python: >=3.6
